sqlalchemy_serializer/__init__.py
sqlalchemy_serializer/serializer.py
sqlalchemy_serializer/lib/__init__.py
sqlalchemy_serializer/lib/fields.py
sqlalchemy_serializer/lib/schema.py
sqlalchemy_serializer/lib/serializable/__init__.py
sqlalchemy_serializer/lib/serializable/base.py
sqlalchemy_serializer/lib/serializable/bytes.py
sqlalchemy_serializer/lib/serializable/date.py
sqlalchemy_serializer/lib/serializable/datetime.py
sqlalchemy_serializer/lib/serializable/decimal.py
sqlalchemy_serializer/lib/serializable/enum.py
sqlalchemy_serializer/lib/serializable/time.py
sqlalchemy_serializer/lib/serializable/uuid.py
sqlalchemy_serializer-1.6.1.dist-info/licenses/LICENSE
sqlalchemy_serializer-1.6.1.dist-info/METADATA
sqlalchemy_serializer-1.6.1.dist-info/WHEEL
sqlalchemy_serializer-1.6.1.dist-info/top_level.txt
sqlalchemy_serializer-1.6.1.dist-info/RECORD
