Metadata-Version: 2.4
Name: sqlalchemy-serializer
Version: 1.6.1
Summary: Mixin for SQLAlchemy models serialization without pain
Author-email: "yuri.boiko" <yuri.boiko.dev@gmail.com>
License: MIT
Project-URL: repository, https://github.com/n0nSmoker/SQLAlchemy-serializer
Keywords: sqlalchemy,serialize,to_dict,JSON
Classifier: Programming Language :: Python :: 3
Classifier: License :: OSI Approved :: MIT License
Classifier: Operating System :: OS Independent
Requires-Python: >=3.10
License-File: LICENSE
Requires-Dist: SQLAlchemy<3.0.0,>=2.0.29
Requires-Dist: psycopg2-binary==2.9.11
Requires-Dist: pytz>=2025.2
Requires-Dist: setuptools>=80.9.0
Dynamic: license-file
